dataset_bias_metrics/__init__.py
dataset_bias_metrics/local_stereotypical.py
dataset_bias_metrics/representational.py
dataset_bias_metrics/stereotypical.py
dataset_bias_metrics/visualization.py
dataset_bias_metrics-0.1.1.dist-info/LICENSE.txt
dataset_bias_metrics-0.1.1.dist-info/METADATA
dataset_bias_metrics-0.1.1.dist-info/WHEEL
dataset_bias_metrics-0.1.1.dist-info/top_level.txt
dataset_bias_metrics-0.1.1.dist-info/RECORD
