Metadata-Version: 2.1
Name: dataset_bias_metrics
Version: 0.1.1
Summary: Dataset demographic bias metrics
Home-page: https://github.com/irisdominguez/dataset_bias_metrics
Download-URL: https://github.com/irisdominguez/dataset_bias_metrics/archive/v_01.tar.gz
Author: Iris Dominguez-Catena
Author-email: iris.dominguez@unavarra.es
License: MIT
Keywords: fairness,machine learning,bias
Classifier: Development Status :: 3 - Alpha
Classifier: Intended Audience :: Developers
Classifier: Topic :: Software Development :: Build Tools
Classifier: License :: OSI Approved :: MIT License
Classifier: Programming Language :: Python :: 3
Classifier: Programming Language :: Python :: 3.8
License-File: LICENSE.txt
Requires-Dist: pandas
Requires-Dist: numpy
Requires-Dist: matplotlib
Requires-Dist: scipy
